bulk_update/__init__.py
bulk_update/helper.py
bulk_update/manager.py
django_bulk_update/__init__.py
django_bulk_update/helper.py
django_bulk_update/manager.py
django_bulk_update-2.1.0.dist-info/DESCRIPTION.rst
django_bulk_update-2.1.0.dist-info/METADATA
django_bulk_update-2.1.0.dist-info/RECORD
django_bulk_update-2.1.0.dist-info/WHEEL
django_bulk_update-2.1.0.dist-info/metadata.json
django_bulk_update-2.1.0.dist-info/top_level.txt
tests/__init__.py
tests/fixtures.py
tests/models.py
tests/test_settings.py
tests/tests.py
